inspiral_range/__init__.py
inspiral_range/__main__.py
inspiral_range/__version__.py
inspiral_range/ang_avg.py
inspiral_range/const.py
inspiral_range/cosmology.py
inspiral_range/inspiral_range.py
inspiral_range/util.py
inspiral_range/waveform.py
inspiral_range/test/2G.txt
inspiral_range/test/CE.txt
inspiral_range/test/CE1.txt
inspiral_range/test/CE2.txt
inspiral_range/test/O2.txt
inspiral_range/test/O3.txt
inspiral_range/test/Voyager.txt
inspiral_range/test/__init__.py
inspiral_range/test/__main__.py
inspiral_range/test/compare.yaml
inspiral_range-0.9.2.dist-info/COPYING
inspiral_range-0.9.2.dist-info/COPYING-GPL-3
inspiral_range-0.9.2.dist-info/METADATA
inspiral_range-0.9.2.dist-info/WHEEL
inspiral_range-0.9.2.dist-info/entry_points.txt
inspiral_range-0.9.2.dist-info/top_level.txt
inspiral_range-0.9.2.dist-info/RECORD
