Metadata-Version: 2.1
Name: inspiral-range
Version: 0.9.2
Summary: GW detector inspiral range calculation tools
Home-page: https://git.ligo.org/gwinc/inspiral_range
Author: Jameson Graef Rollins
Author-email: jameson.rollins@ligo.org
License: GPL-3.0-or-later
Classifier: License :: OSI Approved :: GNU General Public License v3 or later (GPLv3+)
Classifier: Natural Language :: English
Classifier: Programming Language :: Python
License-File: COPYING
License-File: COPYING-GPL-3
Requires-Dist: astropy
Requires-Dist: gpstime
Requires-Dist: numpy
Requires-Dist: pyyaml
Requires-Dist: scipy (>=1.8.0)
Provides-Extra: lal
Requires-Dist: lalsuite ; extra == 'lal'
Provides-Extra: plot
Requires-Dist: matplotlib ; extra == 'plot'
